README.md
setup.py
streamlit_timeline/__init__.py
streamlit_timeline.egg-info/PKG-INFO
streamlit_timeline.egg-info/SOURCES.txt
streamlit_timeline.egg-info/dependency_links.txt
streamlit_timeline.egg-info/requires.txt
streamlit_timeline.egg-info/top_level.txt