Metadata-Version: 2.1
Name: streamlit-timeline
Version: 0.0.2
Summary: A Streamlit custom component to display a timeline
Home-page: https://github.com/innerdoc/streamlit-timeline
Author: Rob van Zoest
Author-email: 
License: UNKNOWN
Project-URL: Github, https://github.com/innerdoc/streamlit-timeline
Project-URL: Homepage, https://www.innerdoc.com
Project-URL: Twitter, https://twitter.com/innerdoc_nlp
Platform: UNKNOWN
Classifier: Programming Language :: Python :: 3
Classifier: Operating System :: OS Independent
Requires-Python: >=3.6
